fast/README.md
fast/__init__.py
fast/entry_points.py
fast/fast.py
fast/bin/DirectML.dll
fast/bin/FAST.dll
fast/bin/InferenceEngineONNXRuntime.dll
fast/bin/InferenceEngineOpenVINO.dll
fast/bin/InferenceEngineTensorFlow.dll
fast/bin/InferenceEngineTensorRT.dll
fast/bin/JKQTCommonSharedLib_Release.dll
fast/bin/JKQTFastPlotterSharedLib_Release.dll
fast/bin/JKQTMathTextSharedLib_Release.dll
fast/bin/JKQTPlotterSharedLib_Release.dll
fast/bin/OpenCL.dll
fast/bin/OpenIGTLink.dll
fast/bin/Qt5Concurrent.dll
fast/bin/Qt5Core.dll
fast/bin/Qt5DBus.dll
fast/bin/Qt5Gui.dll
fast/bin/Qt5Multimedia.dll
fast/bin/Qt5MultimediaWidgets.dll
fast/bin/Qt5Network.dll
fast/bin/Qt5OpenGL.dll
fast/bin/Qt5PrintSupport.dll
fast/bin/Qt5SerialPort.dll
fast/bin/Qt5Sql.dll
fast/bin/Qt5Svg.dll
fast/bin/Qt5Test.dll
fast/bin/Qt5Widgets.dll
fast/bin/Qt5Xml.dll
fast/bin/UFFviewer.exe
fast/bin/_fast.pyd
fast/bin/brotlicommon.dll
fast/bin/brotlidec.dll
fast/bin/brotlienc.dll
fast/bin/cache.json
fast/bin/concrt140.dll
fast/bin/dcmdata.dll
fast/bin/dcmimage.dll
fast/bin/dcmimgle.dll
fast/bin/dcmjpeg.dll
fast/bin/fast_configuration.txt
fast/bin/gna.dll
fast/bin/ijg12.dll
fast/bin/ijg16.dll
fast/bin/ijg8.dll
fast/bin/jpeg62.dll
fast/bin/jxl.dll
fast/bin/jxl_cms.dll
fast/bin/jxl_threads.dll
fast/bin/libcrypto-1_1-x64.dll
fast/bin/libopenslide-1.dll
fast/bin/libssl-1_1-x64.dll
fast/bin/msvcp140.dll
fast/bin/msvcp140_1.dll
fast/bin/msvcp140_2.dll
fast/bin/msvcp140_atomic_wait.dll
fast/bin/msvcp140_codecvt_ids.dll
fast/bin/oflog.dll
fast/bin/ofstd.dll
fast/bin/onnxruntime.dll
fast/bin/onnxruntime_providers_shared.dll
fast/bin/openvino.dll
fast/bin/openvino_auto_batch_plugin.dll
fast/bin/openvino_auto_plugin.dll
fast/bin/openvino_c.dll
fast/bin/openvino_gapi_preproc.dll
fast/bin/openvino_hetero_plugin.dll
fast/bin/openvino_intel_cpu_plugin.dll
fast/bin/openvino_intel_gna_plugin.dll
fast/bin/openvino_intel_gpu_plugin.dll
fast/bin/openvino_ir_frontend.dll
fast/bin/openvino_onnx_frontend.dll
pyfast-4.15.1.dist-info/METADATA
pyfast-4.15.1.dist-info/WHEEL
pyfast-4.15.1.dist-info/entry_points.txt
pyfast-4.15.1.dist-info/top_level.txt
pyfast-4.15.1.dist-info/RECORD
