Metadata-Version: 2.1
Name: pyfast
Version: 4.15.1
Summary: Python bindings of FAST - a framework for high performance medical image computing and visualization on heterogeneous systems utilizing multi-core CPUs and GPUs.
Home-page: https://fast-imaging.github.io
Author: Erik Smistad
Author-email: erik.smistad@sintef.no
License: BSD 2-clause (package include binary dependencies with other licenses, see licenses folder)
Platform: UNKNOWN
Classifier: Development Status :: 5 - Production/Stable
Classifier: Operating System :: Microsoft :: Windows
Classifier: Operating System :: POSIX :: Linux
Classifier: Operating System :: MacOS :: MacOS X
Classifier: Programming Language :: C++
Classifier: Programming Language :: Python :: 3 :: Only
Classifier: Environment :: GPU
Classifier: Topic :: Scientific/Engineering :: Artificial Intelligence
Classifier: Topic :: Scientific/Engineering :: Image Processing
Classifier: Topic :: Scientific/Engineering :: Medical Science Apps.
Classifier: Topic :: Scientific/Engineering :: Visualization
Requires-Python: >=3
